src/__init__.py
src/main.py
s3_package_publisher-0.0.19.dist-info/LICENSE
s3_package_publisher-0.0.19.dist-info/METADATA
s3_package_publisher-0.0.19.dist-info/WHEEL
s3_package_publisher-0.0.19.dist-info/entry_points.txt
s3_package_publisher-0.0.19.dist-info/top_level.txt
s3_package_publisher-0.0.19.dist-info/RECORD
