Metadata-Version: 2.1
Name: s3-package-publisher
Version: 0.0.19
Summary: A Pipenv-friendly CLI tool that packages and publishes your python package to your own S3 repository
Home-page: https://github.com/amamparo/s3-package-publisher
Author: Aaron Mamparo
Author-email: aaronmamparo@gmail.com
License: UNKNOWN
Platform: UNKNOWN
Classifier: Programming Language :: Python :: 3
Classifier: License :: OSI Approved :: MIT License
Classifier: Operating System :: OS Independent
Requires-Python: >= 3.7
Requires-Dist: appdirs (==1.4.4)
Requires-Dist: boto3 (==1.15.5)
Requires-Dist: botocore (==1.18.5)
Requires-Dist: bumpversion (==0.6.0)
Requires-Dist: cached-property (==1.5.2)
Requires-Dist: cerberus (==1.3.2)
Requires-Dist: certifi (==2020.6.20)
Requires-Dist: chardet (==3.0.4)
Requires-Dist: distlib (==0.3.1)
Requires-Dist: importlib-metadata (==2.0.0)
Requires-Dist: orderedmultidict (==1.0.1)
Requires-Dist: pathspec (==0.8.0)
Requires-Dist: pep517 (==0.8.2)
Requires-Dist: pipenv-setup (==3.1.1)
Requires-Dist: pipfile (==0.0.2)
Requires-Dist: regex (==2020.7.14)
Requires-Dist: s3pypi (==0.11.0)
Requires-Dist: s3transfer (==0.3.3)
Requires-Dist: toml (==0.10.1)
Requires-Dist: typed-ast (==1.4.1)
Requires-Dist: urllib3 (==1.25.10) ; python_version != "3.4"
Requires-Dist: jmespath (==0.10.0) ; python_version >= "2.6" and python_version not in "3.0, 3.1, 3.2, 3.3"
Requires-Dist: plette[validation] (==0.2.3) ; python_version >= "2.6" and python_version not in "3.0, 3.1, 3.2, 3.3"
Requires-Dist: pyparsing (==2.4.7) ; python_version >= "2.6" and python_version not in "3.0, 3.1, 3.2, 3.3"
Requires-Dist: attrs (==20.2.0) ; python_version >= "2.7" and python_version not in "3.0, 3.1, 3.2, 3.3"
Requires-Dist: idna (==2.10) ; python_version >= "2.7" and python_version not in "3.0, 3.1, 3.2, 3.3"
Requires-Dist: markupsafe (==1.1.1) ; python_version >= "2.7" and python_version not in "3.0, 3.1, 3.2, 3.3"
Requires-Dist: packaging (==20.4) ; python_version >= "2.7" and python_version not in "3.0, 3.1, 3.2, 3.3"
Requires-Dist: python-dateutil (==2.8.1) ; python_version >= "2.7" and python_version not in "3.0, 3.1, 3.2, 3.3"
Requires-Dist: six (==1.15.0) ; python_version >= "2.7" and python_version not in "3.0, 3.1, 3.2, 3.3"
Requires-Dist: vistir (==0.5.2) ; python_version >= "2.7" and python_version not in "3.0, 3.1, 3.2, 3.3"
Requires-Dist: wheel (==0.33.6) ; python_version >= "2.7" and python_version not in "3.0, 3.1, 3.2, 3.3"
Requires-Dist: click (==7.1.2) ; python_version >= "2.7" and python_version not in "3.0, 3.1, 3.2, 3.3, 3.4"
Requires-Dist: colorama (==0.4.3) ; python_version >= "2.7" and python_version not in "3.0, 3.1, 3.2, 3.3, 3.4"
Requires-Dist: jinja2 (==2.11.2) ; python_version >= "2.7" and python_version not in "3.0, 3.1, 3.2, 3.3, 3.4"
Requires-Dist: pip-shims (==0.5.3) ; python_version >= "2.7" and python_version not in "3.0, 3.1, 3.2, 3.3, 3.4"
Requires-Dist: requests (==2.24.0) ; python_version >= "2.7" and python_version not in "3.0, 3.1, 3.2, 3.3, 3.4"
Requires-Dist: requirementslib (==1.5.13) ; python_version >= "2.7" and python_version not in "3.0, 3.1, 3.2, 3.3, 3.4"
Requires-Dist: tomlkit (==0.7.0) ; python_version >= "2.7" and python_version not in "3.0, 3.1, 3.2, 3.3, 3.4"
Requires-Dist: bump2version (==1.0.0) ; python_version >= "3.5"
Requires-Dist: black (==19.10b0) ; python_version >= "3.6"
Requires-Dist: zipp (==3.2.0) ; python_version >= "3.6"
